{
  "assetCategories": {
    "imperfection": {
      "metal": {
        "scratched": {}
      }
    }
  },
  "averageColor": "#808080",
  "categories": [
    "surface",
    "imperfections",
    "damage"
  ],
  "comp_version": 1,
  "description": "",
  "environment": {
    "biome": "undefined",
    "region": "undefined"
  },
  "highest_available_res": 8192,
  "id": "slnraebc",
  "json": {
    "contentLength": 6712,
    "uri": "slnraebc.json"
  },
  "maps": [
    {
      "averageColor": "#7E7E7E",
      "bitDepth": 32,
      "colorSpace": "Linear",
      "contentLength": 110399490,
      "maxIntensity": 158,
      "mimeType": "image/x-exr",
      "minIntensity": 112,
      "name": "Gloss",
      "physicalSize": "2x2",
      "resolution": "8192x8192",
      "type": "gloss",
      "uri": "slnraebc_8K_Gloss.exr"
    },
    {
      "averageColor": "#7E7E7E",
      "bitDepth": 8,
      "colorSpace": "Linear",
      "contentLength": 28414477,
      "maxIntensity": 158,
      "mimeType": "image/jpeg",
      "minIntensity": 112,
      "name": "Gloss",
      "physicalSize": "2x2",
      "resolution": "8192x8192",
      "type": "gloss",
      "uri": "slnraebc_8K_Gloss.jpg"
    },
    {
      "averageColor": "#020202",
      "bitDepth": 16,
      "colorSpace": "Linear",
      "contentLength": 50032031,
      "maxIntensity": 255,
      "mimeType": "image/x-exr",
      "minIntensity": 0,
      "name": "Mask",
      "physicalSize": "2x2",
      "resolution": "8192x8192",
      "type": "mask",
      "uri": "slnraebc_8K_Mask.exr"
    },
    {
      "averageColor": "#020202",
      "bitDepth": 8,
      "colorSpace": "Linear",
      "contentLength": 18166669,
      "maxIntensity": 255,
      "mimeType": "image/jpeg",
      "minIntensity": 0,
      "name": "Mask",
      "physicalSize": "2x2",
      "resolution": "8192x8192",
      "type": "mask",
      "uri": "slnraebc_8K_Mask.jpg"
    },
    {
      "averageColor": "#818181",
      "bitDepth": 32,
      "colorSpace": "Linear",
      "contentLength": 95232655,
      "maxIntensity": 143,
      "mimeType": "image/x-exr",
      "minIntensity": 97,
      "name": "Roughness",
      "physicalSize": "2x2",
      "resolution": "8192x8192",
      "type": "roughness",
      "uri": "slnraebc_8K_Roughness.exr"
    },
    {
      "averageColor": "#818181",
      "bitDepth": 8,
      "colorSpace": "Linear",
      "contentLength": 28454906,
      "maxIntensity": 143,
      "mimeType": "image/jpeg",
      "minIntensity": 97,
      "name": "Roughness",
      "physicalSize": "2x2",
      "resolution": "8192x8192",
      "type": "roughness",
      "uri": "slnraebc_8K_Roughness.jpg"
    }
  ],
  "meta": [
    {
      "key": "scanArea",
      "name": "Scan Area",
      "value": "2x2 m"
    },
    {
      "key": "height",
      "name": "Height",
      "value": "20 m"
    },
    {
      "key": "tileable",
      "name": "Tileable",
      "value": true
    },
    {
      "key": "texelDensity",
      "name": "Texel Density",
      "value": "4096 px/m"
    },
    {
      "key": "calibration",
      "name": "Calibration",
      "value": "GretagMacbeth ColorChecker Color Rendition Chart"
    },
    {
      "key": "scanner",
      "name": "Scanner",
      "value": "MKX"
    }
  ],
  "models": [],
  "name": "Moderately Scratched Surface",
  "pack": {
    "_id": "pure-imperfections",
    "name": "Pure Imperfections"
  },
  "physicalSize": null,
  "points": 1,
  "previews": {
    "images": [
      {
        "contentLength": 125745,
        "resolution": "360x360",
        "tags": [
          "thumb"
        ],
        "uri": "slnraebc_Grid_360.png"
      },
      {
        "contentLength": 168973,
        "resolution": "420x420",
        "tags": [
          "thumb"
        ],
        "uri": "slnraebc_Grid_420.png"
      },
      {
        "contentLength": 472568,
        "resolution": "720x720",
        "tags": [
          "thumb",
          "retina"
        ],
        "uri": "slnraebc_Grid_720.png"
      },
      {
        "contentLength": 641691,
        "resolution": "840x840",
        "tags": [
          "thumb",
          "retina"
        ],
        "uri": "slnraebc_Grid_840.png"
      },
      {
        "contentLength": 1248288,
        "resolution": "1440x768",
        "tags": [
          "preview"
        ],
        "uri": "slnraebc_Popup_1440.png"
      },
      {
        "contentLength": 2283508,
        "resolution": "1920x1080",
        "tags": [
          "preview"
        ],
        "uri": "slnraebc_Popup_1920.png"
      },
      {
        "contentLength": 4746358,
        "resolution": "2880x1536",
        "tags": [
          "preview",
          "retina"
        ],
        "uri": "slnraebc_Popup_2880.png"
      },
      {
        "contentLength": 8821404,
        "resolution": "3840x2160",
        "tags": [
          "preview",
          "retina"
        ],
        "uri": "slnraebc_Popup_3840.png"
      }
    ],
    "relativeSize": "1x1",
    "scaleReferences": []
  },
  "process_date": "2024-04-17 13:35:05",
  "properties": [],
  "referencePreviews": {
    "maps": [],
    "models": []
  },
  "references": [],
  "revised": false,
  "semanticTags": {
    "architectural_style": {},
    "asset_type": "imperfection",
    "contains": [
      "scratches"
    ],
    "environment": [],
    "industry": [
      "archviz",
      "games",
      "VFX"
    ],
    "interior_exterior": [
      "exterior",
      "interior"
    ],
    "latin_name": [],
    "maxSize": 2,
    "minSize": 2,
    "name": "Moderately Scratched Surface",
    "resolution": 8192,
    "season": [],
    "subject_matter": "manmade",
    "theme": [
      "metal",
      " mild"
    ]
  },
  "tags": [
    "surface imperfection",
    "slightly scratched",
    "scratched metal",
    "grey surface",
    "subtle scratches",
    "rough",
    "tileable",
    "archviz"
  ],
  "texelDensity": 4096,
  "texture_type": "basic",
  "ue_plugin_archives": [
    {
      "contentLength": 63987911,
      "gltfVersion": "2.0",
      "tier": 0,
      "type": "gltf",
      "uri": "ue_plugin_archives/tier_0/slnraebc_tier_0.zip",
      "version": 1
    },
    {
      "contentLength": 20263829,
      "gltfVersion": "2.0",
      "tier": 1,
      "type": "gltf",
      "uri": "ue_plugin_archives/tier_1/slnraebc_tier_1.zip",
      "version": 1
    },
    {
      "contentLength": 5306820,
      "gltfVersion": "2.0",
      "tier": 2,
      "type": "gltf",
      "uri": "ue_plugin_archives/tier_2/slnraebc_tier_2.zip",
      "version": 1
    },
    {
      "contentLength": 1248918,
      "gltfVersion": "2.0",
      "tier": 3,
      "type": "gltf",
      "uri": "ue_plugin_archives/tier_3/slnraebc_tier_3.zip",
      "version": 1
    }
  ],
  "version": 2
}